async_chat_client_geekbrains.egg-info/PKG-INFO
async_chat_client_geekbrains.egg-info/SOURCES.txt
async_chat_client_geekbrains.egg-info/dependency_links.txt
async_chat_client_geekbrains.egg-info/requires.txt
async_chat_client_geekbrains.egg-info/top_level.txt
client_src/__init__.py
client_src/add_contact.py
client_src/client.py
client_src/client_setup.py
client_src/database.py
client_src/del_contact.py
client_src/main_window.py
client_src/main_window_conv.py
client_src/start_dialog.py
client_src/transport.py
server_src/__init__.py
server_src/auth.py
server_src/server.py
server_src/server_core.py
server_src/server_database.py
server_src/server_gui.py
server_src/server_setup.py