Metadata-Version: 2.1
Name: async-chat-client-geekbrains
Version: 0.0.2
Summary: mess_client
Home-page: UNKNOWN
Author: Polyakov
Author-email: ae.polyakov@mail.ru
License: UNKNOWN
Platform: UNKNOWN
